{
  "common": {
    "edit": "تعديل",
    "delete": "حذف",
    "cancel": "إلغاء",
    "submit": "إرسال",
    "loading": "جاري التحميل...",
    "error": "خطأ",
    "success": "نجاح",
    "save": "حفظ",
    "close": "إغلاق",
    "notAvailable": "غير متوفر",
    "errorMessages": {
      "unauthorized": "ليس لديك صلاحية. الرجاء إعادة تسجيل الدخول"
    }
  },
  "auth": {
    "login": {
      "title": "تسجيل الدخول",
      "username": "اسم المستخدم:",
      "password": "كلمة المرور:",
      "loginButton": "تسجيل الدخول",
      "noAccount": "ليس لديك حساب؟",
      "register": "التسجيل"
    },
    "register": {
      "title": "مرحبًا بك في Fleet Master",
      "subtitle": "ابدأ بإدارة أسطولك بسهولة. سجّل الآن لتتبع أسطولك والبقاء منظمًا.",
      "registerButton": "تسجيل",
      "hasAccount": "هل لديك حساب بالفعل؟",
      "login": "تسجيل الدخول",
      "form": {
        "firstName": "الاسم الأول",
        "lastName": "اسم العائلة",
        "username": "اسم المستخدم",
        "email": "البريد الإلكتروني",
        "phone": "رقم الهاتف",
        "password": "كلمة المرور",
        "confirmPassword": "تأكيد كلمة المرور",
        "addressInformationTitle": "معلومات العنوان (اختياري)",
        "collapseAddress": "إضافة عنوان",
        "toggleAddress": "إخفاء",
        "street": "عنوان الشارع",
        "city": "المدينة",
        "state": "الولاية/المقاطعة",
        "country": "البلد",
        "zip": "الرمز البريدي"
      },
      "agreement": {
        "title": "بالمتابعة أنت توافق على",
        "terms": "شروط الخدمة",
        "policy": "سياسة الخصوصية",
        "and": "و"
      }
    }
  },
  "layout": {
    "dashboard": {
      "dashboard": "لوحة التحكم",
      "vehicles": "المركبات",
      "drivers": "السائقون",
      "maintenance": "الصيانة",
      "reports": "نظرة عامة على التقارير",
      "logout": "تسجيل الخروج"
    },
    "maintenance": {
      "title": "الصيانة",
      "overview": "نظرة عامة على الصيانة",
      "parts": "قطع الغيار",
      "partProviders": "موردو قطع الغيار",
      "serviceProviders": "مقدمو الخدمة",
      "reports": "التقارير",
      "exit": "خروج"
    }
  },
  "pages": {
    "vehicle": {
      "title": "إدارة المركبات",
      "subtitle": "عرض وإدارة أسطولك",
      "addButton": "إضافة مركبة",
      "filter": {
        "status": "تصفية حسب الحالة",
        "all": "الكل",
        "active": "نشط",
        "onLeave": "في إجازة",
        "outOfService": "خارج الخدمة"
      },
      "search": "ابحث عن مركبات...",
      "resultsCount": {
        "single": "مركبة واحدة",
        "plural": "مركبات"
      },
      "noResults": {
        "withSearch": "لا توجد مركبات تطابق بحثك",
        "empty": "لا توجد مركبات متاحة في الأسطول",
        "tryDifferent": "جرب بحثًا مختلفًا أو أزل الفلاتر",
        "addFirst": "أضف مركبتك الأولى باستخدام الزر بالأعلى"
      },
      "card": {
        "generalInfo": "المعلومات العامة",
        "name": "اسم المركبة",
        "purchaseDate": "تاريخ الشراء",
        "capacity": "السعة",
        "mileage": "عدد الأميال",
        "maintenanceInfo": "معلومات الصيانة",
        "nextServiceDue": "موعد الصيانة القادمة",
        "lastServiceDate": "تاريخ آخر صيانة",
        "documentation": "المستندات",
        "licenseExpiry": "انتهاء الرخصة",
        "insuranceExpiry": "انتهاء التأمين",
        "status": "الحالة",
        "maintenance": "الصيانة",
        "notes": "ملاحظات"
      },
      "dialog": {
        "add": "إضافة مركبة جديدة",
        "edit": "تعديل المركبة",
        "registration": "رقم التسجيل",
        "vin": "رقم الهيكل (VIN)",
        "type": {
          "title": "نوع المركبة",
          "types": {
            "CAR": "سيارة",
            "MOTORCYCLE": "دراجة نارية",
            "TRUCK": "شاحنة",
            "VAN": "فان"
          }
        },
        "status": {
          "title": "حالة المركبة",
          "statuses": {
            "ACTIVE": "نشط",
            "IN_MAINTENANCE": "قيد الصيانة",
            "OUT_OF_SERVICE": "خارج الخدمة"
          }
        },
        "notes": "ملاحظات",
        "make": "العلامة التجارية",
        "model": "الموديل",
        "year": "السنة",
        "color": "اللون",
        "fuel": {
          "title": "نوع الوقود",
          "types": {
            "GASOLINE": "بنزين",
            "DIESEL": "ديزل",
            "ELECTRIC": "كهربائي",
            "HYBRID": "هجين"
          }
        },
        "mileage": "عدد الأميال",
        "capacity": "السعة",
        "purchaseDate": "تاريخ الشراء",
        "lastServiceDate": "تاريخ آخر صيانة",
        "nextServiceDue": "موعد الصيانة القادمة",
        "insurancePolicyNum": "رقم بوليصة التأمين",
        "insuranceExpiryDate": "تاريخ انتهاء التأمين",
        "licenseExpiryDate": "تاريخ انتهاء الرخصة",
        "addButton": "إضافة مركبة",
        "updateButton": "تحديث المركبة",
        "sections": {
          "basic": "المعلومات الأساسية",
          "specs": "مواصفات المركبة",
          "dates": "التواريخ",
          "legal": "المعلومات القانونية والتأمين"
        }
      },
      "deleteDialog": {
        "title": "حذف المركبة",
        "subtitle": "هل أنت متأكد من رغبتك في حذف هذه المركبة؟ لا يمكن التراجع عن هذا الإجراء."
      },
      "snackbar": {
        "added": "تمت إضافة المركبة بنجاح",
        "updated": "تم تحديث المركبة بنجاح",
        "deleted": "تم حذف المركبة بنجاح"
      },
      "errors": {
        "createError": "فشل في إنشاء المركبة",
        "updateError": "فشل في تحديث المركبة",
        "deleteError": "فشل في حذف المركبة",
        "requiredFields": "يرجى ملء جميع الحقول المطلوبة"
      },
      "maintenance": {
        "overview": {
          "title": "نظرة عامة على الصيانة",
          "summaryMetrics": {
            "tabs": {
              "yearly": "نظرة عامة سنوية",
              "monthly": "التفصيل الشهري"
            },
            "yearly": {
              "totalCost": {
                "title": "إجمالي تكلفة الصيانة",
                "events": "عمليات صيانة"
              },
              "byType": {
                "title": "الصيانة حسب النوع",
                "preventive": "وقائية",
                "curative": "علاجية"
              },
              "yearComparison": {
                "title": "المقارنة السنوية",
                "higher": "أعلى من العام السابق",
                "lower": "أقل من العام السابق"
              }
            },
            "monthly": {
              "title": "تكلفة الصيانة الشهرية",
              "events": "عمليات صيانة",
              "breakdown": {
                "title": "التفصيل الشهري",
                "preventive": "وقائية",
                "curative": "علاجية"
              },
              "monthChange": {
                "title": "التغيير الشهري",
                "higher": "أعلى من",
                "lower": "أقل من"
              },
              "yearChange": {
                "title": "التغيير السنوي الشهري",
                "higher": "أعلى من نفس الشهر في العام الماضي",
                "lower": "أقل من نفس الشهر في العام الماضي"
              }
            },
            "months": {
              "january": "يناير",
              "february": "فبراير",
              "march": "مارس",
              "april": "أبريل",
              "may": "مايو",
              "june": "يونيو",
              "july": "يوليو",
              "august": "أغسطس",
              "september": "سبتمبر",
              "october": "أكتوبر",
              "november": "نوفمبر",
              "december": "ديسمبر"
            }
          },
          "vehiclePanel": {
            "title": "تفاصيل المركبة",
            "registration": "رقم التسجيل",
            "vehicle": "المركبة",
            "vin": "رقم التعريف",
            "type": "النوع",
            "mileage": "المسافة المقطوعة",
            "status": "الحالة",
            "lastService": "آخر صيانة",
            "nextServiceDue": "موعد الصيانة القادمة",
            "notAvailable": "غير متوفر",
            "km": "كم"
          },
          "yearlyComparisonChart": {
            "title": "مقارنة التكاليف السنوية",
            "legend": {
              "currentYear": "العام الحالي",
              "prevYear": "العام السابق"
            },
            "axis": {
              "dollar": "$",
              "months": {
                "jan": "يناير",
                "feb": "فبراير",
                "mar": "مارس",
                "apr": "أبريل",
                "may": "مايو",
                "jun": "يونيو",
                "jul": "يوليو",
                "aug": "أغسطس",
                "sep": "سبتمبر",
                "oct": "أكتوبر",
                "nov": "نوفمبر",
                "dec": "ديسمبر"
              }
            },
            "tooltip": {
              "cost": "التكلفة"
            }
          },
          "timeline": {
            "title": "الجدول الزمني للصيانة",
            "noEvents": "لم يتم العثور على أحداث صيانة للفترة الزمنية المحددة.",
            "legend": {
              "preventive": "وقائية",
              "curative": "علاجية"
            },
            "tooltip": {
              "date": "التاريخ",
              "type": "النوع",
              "cost": "التكلفة",
              "description": "الوصف"
            },
            "preventiveLabel": "و",
            "curativeLabel": "ع"
          },
          "reports": {
            "title": "تقارير الصيانة",
            "list": {
              "goBack": "العودة",
              "search": "البحث في التقارير...",
              "type": {
                "title": "النوع",
                "types": {
                  "ALL": "جميع الأنواع",
                  "PREVENTIVE": "وقائية",
                  "CURATIVE": "علاجية"
                }
              },
              "sort": {
                "title": "ترتيب حسب",
                "types": {
                  "date_desc": "الأحدث أولاً",
                  "date_asc": "الأقدم أولاً",
                  "cost_desc": "الأعلى تكلفة",
                  "cost_asc": "الأقل تكلفة"
                }
              },
              "resultSummary": {
                "plural": "تقارير وجدت",
                "single": "تقرير وجد"
              },
              "card": {
                "unknown": "غير معروف",
                "vehicle": "المركبة",
                "label": {
                  "period": "الفترة",
                  "mileage": "المسافة المقطوعة",
                  "totalCost": "إجمالي التكلفة",
                  "providers": "مقدمو الخدمات"
                },
                "value": {
                  "to": "إلى",
                  "notRecorded": "غير مسجل"
                },
                "actions": {
                  "edit": "تعديل التقرير",
                  "delete": "حذف التقرير",
                  "less": "عرض أقل",
                  "more": "عرض المزيد"
                },
                "parts": {
                  "title": "قطع الغيار المستخدمة",
                  "unnamed": "قطعة غيار بدون اسم",
                  "quantity": "الكمية: 1",
                  "cost": "إجمالي قطع الغيار",
                  "none": "لم يتم استخدام قطع غيار في هذه الصيانة"
                },
                "services": {
                  "title": "مقدمو الخدمة",
                  "unknown": "مقدم خدمة غير معروف",
                  "cost": "إجمالي الخدمات",
                  "none": "لم يتم استخدام مقدمي خدمة خارجيين لهذه الصيانة"
                }
              },
              "none": "لم يتم العثور على تقارير صيانة",
              "try": "حاول تعديل البحث أو الفلاتر"
            },
            "deleteDialog": {
              "title": "تأكيد الحذف",
              "subtitle": "هل أنت متأكد من رغبتك في حذف تقرير الصيانة هذا؟ لا يمكن التراجع عن هذا الإجراء."
            },
            "dialog": {
              "title": "تقرير صيانة جديد",
              "type": {
                "title": "نوع الصيانة",
                "types": {
                  "PREVENTIVE": "وقائية",
                  "CURATIVE": "علاجية"
                }
              },
              "mileage": "المسافة المقطوعة",
              "startDate": "تاريخ البدء",
              "endDate": "تاريخ الانتهاء",
              "description": "الوصف",
              "part": {
                "title": "شراء قطع الغيار",
                "name": "اسم قطعة الغيار",
                "notFound": "قطعة الغيار غير موجودة",
                "provider": {
                  "title": "مورد قطع الغيار"
                },
                "purchaseDate": "تاريخ الشراء",
                "cost": "التكلفة",
                "actions": {
                  "add": "إضافة قطعة غيار",
                  "addPurchase": "إضافة شراء قطعة غيار"
                }
              },
              "service": {
                "title": "خدمات الإصلاح",
                "provider": {
                  "title": "مقدم الخدمة"
                },
                "serviceDate": "تاريخ الخدمة",
                "cost": "التكلفة",
                "description": "الوصف",
                "actions": {
                  "add": "إضافة خدمة",
                  "addEvent": "إضافة حدث خدمة"
                }
              },
              "actions": {
                "save": "حفظ التقرير"
              }
            }
          }
        },
        "parts": {
          "title": "إدارة قطع الغيار",
          "subtitle": "فيما يلي قائمة قطع الغيار.",
          "search": "البحث عن قطع الغيار...",
          "addButton": "إضافة قطعة غيار",
          "resultsCount": {
            "found": "نتائج وجدت",
            "total": "إجمالي قطع الغيار"
          },
          "noResults": {
            "withSearch": "لا توجد قطع غيار تطابق بحثك",
            "empty": "لا توجد قطع غيار متاحة. أضف أول قطعة غيار!"
          },
          "pagination": {
            "itemsPerPage": "العناصر في الصفحة:",
            "of": "من"
          },
          "dialog": {
            "add": "إضافة قطعة غيار جديدة",
            "edit": "تعديل قطعة الغيار",
            "name": "اسم قطعة الغيار",
            "description": "الوصف",
            "actions": {
              "cancel": "إلغاء",
              "add": "إضافة قطعة غيار",
              "save": "حفظ التغييرات"
            }
          },
          "deleteDialog": {
            "title": "تأكيد الحذف",
            "subtitle": "هل أنت متأكد من رغبتك في حذف قطعة الغيار ؟ لا يمكن التراجع عن هذا الإجراء.",
            "actions": {
              "cancel": "إلغاء",
              "delete": "حذف"
            }
          },
          "errors": {
            "createError": "خطأ أثناء إنشاء قطعة الغيار",
            "updateError": "خطأ أثناء تحديث قطعة الغيار",
            "deleteError": "خطأ أثناء حذف قطعة الغيار"
          }
        },
        "partProviders": {
          "title": "قائمة موردي قطع الغيار",
          "subtitle": "فيما يلي قائمة موردي قطع الغيار.",
          "addButton": "إضافة مورد قطع غيار",
          "dialog": {
            "add": "إضافة مورد قطع غيار جديد",
            "edit": "تعديل مورد قطع الغيار",
            "name": "اسم المورد",
            "address": "العنوان",
            "phoneNumber": "رقم الهاتف",
            "actions": {
              "cancel": "إلغاء",
              "add": "إضافة مورد",
              "save": "حفظ التغييرات"
            }
          },
          "deleteDialog": {
            "title": "تأكيد الحذف",
            "subtitle": "هل أنت متأكد من رغبتك في حذف مورد قطع الغيار هذا؟ لا يمكن التراجع عن هذا الإجراء.",
            "actions": {
              "cancel": "إلغاء",
              "delete": "حذف"
            }
          },
          "errors": {
            "createError": "خطأ أثناء إنشاء مورد قطع الغيار",
            "updateError": "خطأ أثناء تحديث مورد قطع الغيار",
            "deleteError": "خطأ أثناء حذف مورد قطع الغيار"
          }
        },
        "serviceProviders": {
          "title": "قائمة مزودي الخدمة",
          "subtitle": "فيما يلي قائمة مزودي الخدمة.",
          "addButton": "إضافة مزود خدمة",
          "dialog": {
            "add": "إضافة مزود خدمة جديد",
            "edit": "تعديل مزود الخدمة",
            "name": "اسم المزود",
            "address": "العنوان",
            "phoneNumber": "رقم الهاتف",
            "serviceType": "نوع الخدمة",
            "serviceTypes": {
              "MECHANIC": "ميكانيكي",
              "ELECTRICIAN": "كهربائي",
              "CLEANING": "تنظيف"
            },
            "actions": {
              "cancel": "إلغاء",
              "add": "إضافة مزود",
              "save": "حفظ التغييرات"
            }
          },
          "deleteDialog": {
            "title": "تأكيد الحذف",
            "subtitle": "هل أنت متأكد من أنك تريد حذف مزود الخدمة هذا؟ لا يمكن التراجع عن هذا الإجراء.",
            "actions": {
              "cancel": "إلغاء",
              "delete": "حذف"
            }
          },
          "errors": {
            "createError": "خطأ أثناء إنشاء مزود الخدمة",
            "updateError": "خطأ أثناء تحديث مزود الخدمة",
            "deleteError": "خطأ أثناء حذف مزود الخدمة"
          }
        },
        "reports": {
          "title": "نظرة عامة على الصيانة",
          "addButton": "تقرير جديد",
          "badgeText": "التواريخ ذات الشارات تشير إلى أنشطة الصيانة المجدولة",
          "count": "إجمالي سجلات الصيانة",
          "snack": {
            "add": "تمت إضافة التقرير بنجاح!",
            "edit": "تم تعديل التقرير بنجاح!",
            "delete": "تم حذف التقرير بنجاح!"
          }
        }
      }
    },
    "driver": {
      "title": "إدارة السائقين",
      "subtitle": "عرض وإدارة سائقي أسطولك",
      "addButton": "إضافة سائق",
      "search": "البحث عن سائقين...",
      "filter": {
        "status": "تصفية حسب الحالة",
        "all": "جميع الحالات",
        "active": "نشط",
        "onLeave": "في إجازة",
        "inactive": "غير نشط"
      },
      "resultsCount": {
        "single": "سائق واحد",
        "plural": "سائقين"
      },
      "noResults": {
        "withSearch": "لا يوجد سائقين مطابقين لمعايير البحث",
        "empty": "لا يوجد سائقين متاحين في أسطولك",
        "tryDifferent": "جرب بحثًا مختلفًا أو قم بمسح عوامل التصفية",
        "addFirst": "أضف أول سائق باستخدام الزر أعلاه"
      },
      "card": {
        "licenseStatus": {
          "expired": "منتهية الصلاحية",
          "expiringSoon": "تنتهي قريباً",
          "valid": "سارية المفعول"
        },
        "common": {
          "edit": "تعديل",
          "delete": "حذف"
        },
        "contactInfo": "معلومات الاتصال",
        "drivingInfo": "معلومات القيادة",
        "license": "رخصة القيادة",
        "licenseExpiry": "تاريخ انتهاء الرخصة",
        "dob": "تاريخ الميلاد",
        "hireDate": "تاريخ التوظيف",
        "emergencyContact": "جهة اتصال في حالات الطوارئ",
        "assignedVehicle": "المركبة المخصصة",
        "notes": "ملاحظات"
      },
      "dialog": {
        "add": "إضافة سائق جديد",
        "edit": "تعديل بيانات السائق",
        "assignedVehicle": "المركبة المخصصة",
        "noVehicle": "لا توجد مركبة مخصصة",
        "sections": {
          "personal": "المعلومات الشخصية",
          "license": "معلومات الرخصة",
          "address": "معلومات العنوان",
          "emergency": "جهة اتصال للطوارئ",
          "vehicle": "تخصيص المركبة"
        },
        "firstName": "الاسم الأول",
        "lastName": "اسم العائلة",
        "phone": "رقم الهاتف",
        "email": "البريد الإلكتروني",
        "dob": "تاريخ الميلاد",
        "status": "حالة التوظيف",
        "statusOptions": {
          "active": "نشط",
          "onLeave": "في إجازة",
          "inactive": "غير نشط"
        },
        "hireDate": "تاريخ التوظيف",
        "licenseNumber": "رقم الرخصة",
        "licenseExpiry": "تاريخ انتهاء الرخصة",
        "address": "العنوان",
        "city": "المدينة",
        "state": "المحافظة/الولاية",
        "zipCode": "الرمز البريدي",
        "country": "البلد",
        "emergencyName": "اسم جهة اتصال الطوارئ",
        "emergencyPhone": "هاتف جهة اتصال الطوارئ",
        "notes": "ملاحظات",
        "addButton": "إضافة سائق",
        "updateButton": "تحديث بيانات السائق"
      },
      "deleteDialog": {
        "title": "حذف السائق",
        "subtitle": "هل أنت متأكد من رغبتك في حذف هذا السائق؟ لا يمكن التراجع عن هذا الإجراء."
      },
      "snackbar": {
        "added": "تمت إضافة السائق بنجاح",
        "updated": "تم تحديث بيانات السائق بنجاح",
        "deleted": "تم حذف السائق بنجاح"
      },
      "errors": {
        "fetchError": "فشل في تحميل بيانات السائقين",
        "createError": "فشل في إنشاء سائق جديد",
        "updateError": "فشل في تحديث بيانات السائق",
        "deleteError": "فشل في حذف السائق",
        "requiredFields": "يرجى ملء جميع الحقول المطلوبة"
      }
    }
  }
}

